odoo/addons/l10n_fr_das2/README.rst
odoo/addons/l10n_fr_das2/__init__.py
odoo/addons/l10n_fr_das2/__manifest__.py
odoo/addons/l10n_fr_das2/demo/demo.xml
odoo/addons/l10n_fr_das2/i18n/fr.po
odoo/addons/l10n_fr_das2/i18n/l10n_fr_das2.pot
odoo/addons/l10n_fr_das2/models/__init__.py
odoo/addons/l10n_fr_das2/models/l10n_fr_das2.py
odoo/addons/l10n_fr_das2/models/res_partner.py
odoo/addons/l10n_fr_das2/readme/CONFIGURE.rst
odoo/addons/l10n_fr_das2/readme/CONTRIBUTORS.rst
odoo/addons/l10n_fr_das2/readme/DESCRIPTION.rst
odoo/addons/l10n_fr_das2/readme/INSTALL.rst
odoo/addons/l10n_fr_das2/readme/USAGE.rst
odoo/addons/l10n_fr_das2/security/das2_security.xml
odoo/addons/l10n_fr_das2/security/ir.model.access.csv
odoo/addons/l10n_fr_das2/static/description/icon.png
odoo/addons/l10n_fr_das2/static/description/index.html
odoo/addons/l10n_fr_das2/tests/__init__.py
odoo/addons/l10n_fr_das2/tests/test_das2.py
odoo/addons/l10n_fr_das2/views/l10n_fr_das2.xml
odoo/addons/l10n_fr_das2/views/res_partner.xml
odoo14_addon_l10n_fr_das2-14.0.4.0.0.dist-info/METADATA
odoo14_addon_l10n_fr_das2-14.0.4.0.0.dist-info/WHEEL
odoo14_addon_l10n_fr_das2-14.0.4.0.0.dist-info/top_level.txt
odoo14_addon_l10n_fr_das2-14.0.4.0.0.dist-info/RECORD
