Metadata-Version: 2.1
Name: odoo14-addon-l10n_fr_das2
Version: 14.0.4.0.0
Summary: DAS2 (France)
Home-page: https://github.com/OCA/l10n-france
Author: Akretion,Odoo Community Association (OCA)
Author-email: support@odoo-community.org
License: AGPL-3
Classifier: Programming Language :: Python
Classifier: Framework :: Odoo
Classifier: Framework :: Odoo :: 14.0
Classifier: License :: OSI Approved :: GNU Affero General Public License v3
Requires-Python: >=3.6
Requires-Dist: odoo14-addon-l10n-fr-cog
Requires-Dist: odoo14-addon-l10n-fr-siret
Requires-Dist: odoo<14.1dev,>=14.0a
Requires-Dist: pyfrdas2>=0.10
Requires-Dist: python-stdnum
